{"v":"5.5.7","meta":{"g":"LottieFiles AE 0.1.20","a":"","k":"","d":"","tc":""},"fr":29.9700012207031,"ip":0,"op":47.0000019143492,"w":1500,"h":500,"nm":"button","ddd":0,"assets":[],"fonts":{"list":[{"fName":"MyriadPro-Semibold","fFamily":"Myriad Pro","fStyle":"Semibold","ascent":70.9991455078125}]},"layers":[{"ddd":0,"ind":1,"ty":4,"nm":"Shape Layer 5","sr":1,"ks":{"o":{"a":0,"k":100,"ix":11},"r":{"a":0,"k":0,"ix":10},"p":{"a":0,"k":[750,250,0],"ix":2},"a":{"a":0,"k":[0,0,0],"ix":1},"s":{"a":0,"k":[100,100,100],"ix":6}},"ao":0,"shapes":[{"ty":"gr","it":[{"ind":0,"ty":"sh","ix":1,"ks":{"a":0,"k":{"i":[[0,0],[0,0]],"o":[[0,0],[0,0]],"v":[[134,98],[216,198]],"c":false},"ix":2},"nm":"Path 1","mn":"ADBE Vector Shape - Group","hd":false},{"ty":"st","c":{"a":0,"k":[0.980698529412,0.95262816186,0.567987898284,1],"ix":3},"o":{"a":0,"k":100,"ix":4},"w":{"a":0,"k":16,"ix":5},"lc":1,"lj":1,"ml":4,"bm":0,"nm":"Stroke 1","mn":"ADBE Vector Graphic - Stroke","hd":false},{"ty":"tr","p":{"a":0,"k":[0,0],"ix":2},"a":{"a":0,"k":[0,0],"ix":1},"s":{"a":0,"k":[100,100],"ix":3},"r":{"a":0,"k":0,"ix":6},"o":{"a":0,"k":100,"ix":7},"sk":{"a":0,"k":0,"ix":4},"sa":{"a":0,"k":0,"ix":5},"nm":"Transform"}],"nm":"Shape 3","np":3,"cix":2,"bm":0,"ix":1,"mn":"ADBE Vector Group","hd":false},{"ty":"gr","it":[{"ind":0,"ty":"sh","ix":1,"ks":{"a":0,"k":{"i":[[0,0],[23.341,-14.223],[22.909,-11.454],[18.706,2.647]],"o":[[-18.886,1.259],[-21.872,13.328],[-23.881,11.941],[0,0]],"v":[[-134,118],[-214,136],[-262,196],[-342,200]],"c":false},"ix":2},"nm":"Path 1","mn":"ADBE Vector Shape - Group","hd":false},{"ty":"st","c":{"a":0,"k":[0.920128703117,0.52126532793,0.716737747192,1],"ix":3},"o":{"a":0,"k":100,"ix":4},"w":{"a":0,"k":16,"ix":5},"lc":1,"lj":1,"ml":4,"bm":0,"nm":"Stroke 1","mn":"ADBE Vector Graphic - Stroke","hd":false},{"ty":"tr","p":{"a":0,"k":[0,0],"ix":2},"a":{"a":0,"k":[0,0],"ix":1},"s":{"a":0,"k":[100,100],"ix":3},"r":{"a":0,"k":0,"ix":6},"o":{"a":0,"k":100,"ix":7},"sk":{"a":0,"k":0,"ix":4},"sa":{"a":0,"k":0,"ix":5},"nm":"Transform"}],"nm":"Shape 2","np":3,"cix":2,"bm":0,"ix":2,"mn":"ADBE Vector Group","hd":false},{"ty":"gr","it":[{"ind":0,"ty":"sh","ix":1,"ks":{"a":0,"k":{"i":[[0,0],[-11.614,13.852],[-13.453,15.785],[-14.511,4.033]],"o":[[12.795,-2.383],[13.325,-15.893],[13.833,-16.231],[0,0]],"v":[[108,-126],[158,-147],[175.635,-206.67],[233,-235]],"c":false},"ix":2},"nm":"Path 1","mn":"ADBE Vector Shape - Group","hd":false},{"ty":"st","c":{"a":0,"k":[0.567987918854,0.980698525906,0.884500563145,1],"ix":3},"o":{"a":0,"k":100,"ix":4},"w":{"a":0,"k":16,"ix":5},"lc":1,"lj":1,"ml":4,"bm":0,"nm":"Stroke 1","mn":"ADBE Vector Graphic - Stroke","hd":false},{"ty":"tr","p":{"a":0,"k":[0,0],"ix":2},"a":{"a":0,"k":[0,0],"ix":1},"s":{"a":0,"k":[100,100],"ix":3},"r":{"a":0,"k":0,"ix":6},"o":{"a":0,"k":100,"ix":7},"sk":{"a":0,"k":0,"ix":4},"sa":{"a":0,"k":0,"ix":5},"nm":"Transform"}],"nm":"Shape 1","np":3,"cix":2,"bm":0,"ix":3,"mn":"ADBE Vector Group","hd":false},{"ty":"tm","s":{"a":1,"k":[{"i":{"x":[0.667],"y":[1]},"o":{"x":[0.333],"y":[0]},"t":12,"s":[0]},{"t":27.0000010997325,"s":[100]}],"ix":1},"e":{"a":1,"k":[{"i":{"x":[0.667],"y":[1]},"o":{"x":[0.333],"y":[0]},"t":27,"s":[0]},{"t":43.0000017514259,"s":[100]}],"ix":2},"o":{"a":0,"k":0,"ix":3},"m":1,"ix":4,"nm":"Trim Paths 1","mn":"ADBE Vector Filter - Trim","hd":false}],"ip":0,"op":47.0000019143492,"st":0,"bm":0},{"ddd":0,"ind":2,"ty":4,"nm":"Shape Layer 7","sr":1,"ks":{"o":{"a":0,"k":39,"ix":11},"r":{"a":0,"k":0,"ix":10},"p":{"a":0,"k":[758,256,0],"ix":2},"a":{"a":0,"k":[0,0,0],"ix":1},"s":{"a":0,"k":[100,100,100],"ix":6}},"ao":0,"shapes":[{"ty":"gr","it":[{"ind":0,"ty":"sh","ix":1,"ks":{"a":0,"k":{"i":[[0,0],[0,0]],"o":[[0,0],[0,0]],"v":[[134,98],[216,198]],"c":false},"ix":2},"nm":"Path 1","mn":"ADBE Vector Shape - Group","hd":false},{"ty":"st","c":{"a":0,"k":[0.278010379567,0.296622721354,0.307659313725,1],"ix":3},"o":{"a":0,"k":100,"ix":4},"w":{"a":0,"k":16,"ix":5},"lc":1,"lj":1,"ml":4,"bm":0,"nm":"Stroke 1","mn":"ADBE Vector Graphic - Stroke","hd":false},{"ty":"tr","p":{"a":0,"k":[0,0],"ix":2},"a":{"a":0,"k":[0,0],"ix":1},"s":{"a":0,"k":[100,100],"ix":3},"r":{"a":0,"k":0,"ix":6},"o":{"a":0,"k":100,"ix":7},"sk":{"a":0,"k":0,"ix":4},"sa":{"a":0,"k":0,"ix":5},"nm":"Transform"}],"nm":"Shape 3","np":3,"cix":2,"bm":0,"ix":1,"mn":"ADBE Vector Group","hd":false},{"ty":"gr","it":[{"ind":0,"ty":"sh","ix":1,"ks":{"a":0,"k":{"i":[[0,0],[23.341,-14.223],[22.909,-11.454],[18.706,2.647]],"o":[[-18.886,1.259],[-21.872,13.328],[-23.881,11.941],[0,0]],"v":[[-134,118],[-214,136],[-262,196],[-342,200]],"c":false},"ix":2},"nm":"Path 1","mn":"ADBE Vector Shape - Group","hd":false},{"ty":"st","c":{"a":0,"k":[0.278010379567,0.296622721354,0.307659313725,1],"ix":3},"o":{"a":0,"k":100,"ix":4},"w":{"a":0,"k":16,"ix":5},"lc":1,"lj":1,"ml":4,"bm":0,"nm":"Stroke 1","mn":"ADBE Vector Graphic - Stroke","hd":false},{"ty":"tr","p":{"a":0,"k":[0,0],"ix":2},"a":{"a":0,"k":[0,0],"ix":1},"s":{"a":0,"k":[100,100],"ix":3},"r":{"a":0,"k":0,"ix":6},"o":{"a":0,"k":100,"ix":7},"sk":{"a":0,"k":0,"ix":4},"sa":{"a":0,"k":0,"ix":5},"nm":"Transform"}],"nm":"Shape 2","np":3,"cix":2,"bm":0,"ix":2,"mn":"ADBE Vector Group","hd":false},{"ty":"gr","it":[{"ind":0,"ty":"sh","ix":1,"ks":{"a":0,"k":{"i":[[0,0],[-11.614,13.852],[-13.453,15.785],[-14.511,4.033]],"o":[[12.795,-2.383],[13.325,-15.893],[13.833,-16.231],[0,0]],"v":[[108,-126],[158,-147],[175.635,-206.67],[233,-235]],"c":false},"ix":2},"nm":"Path 1","mn":"ADBE Vector Shape - Group","hd":false},{"ty":"st","c":{"a":0,"k":[0.278010379567,0.296622721354,0.307659313725,1],"ix":3},"o":{"a":0,"k":100,"ix":4},"w":{"a":0,"k":16,"ix":5},"lc":1,"lj":1,"ml":4,"bm":0,"nm":"Stroke 1","mn":"ADBE Vector Graphic - Stroke","hd":false},{"ty":"tr","p":{"a":0,"k":[0,0],"ix":2},"a":{"a":0,"k":[0,0],"ix":1},"s":{"a":0,"k":[100,100],"ix":3},"r":{"a":0,"k":0,"ix":6},"o":{"a":0,"k":100,"ix":7},"sk":{"a":0,"k":0,"ix":4},"sa":{"a":0,"k":0,"ix":5},"nm":"Transform"}],"nm":"Shape 1","np":3,"cix":2,"bm":0,"ix":3,"mn":"ADBE Vector Group","hd":false},{"ty":"tm","s":{"a":1,"k":[{"i":{"x":[0.667],"y":[1]},"o":{"x":[0.333],"y":[0]},"t":12,"s":[0]},{"t":27.0000010997325,"s":[100]}],"ix":1},"e":{"a":1,"k":[{"i":{"x":[0.667],"y":[1]},"o":{"x":[0.333],"y":[0]},"t":27,"s":[0]},{"t":43.0000017514259,"s":[100]}],"ix":2},"o":{"a":0,"k":0,"ix":3},"m":1,"ix":4,"nm":"Trim Paths 1","mn":"ADBE Vector Filter - Trim","hd":false}],"ip":0,"op":47.0000019143492,"st":0,"bm":0},{"ddd":0,"ind":3,"ty":4,"nm":"Shape Layer 4","sr":1,"ks":{"o":{"a":1,"k":[{"i":{"x":[0.833],"y":[0.833]},"o":{"x":[0.167],"y":[0.167]},"t":41,"s":[100]},{"t":45.0000018328876,"s":[0]}],"ix":11},"r":{"a":0,"k":0,"ix":10},"p":{"a":1,"k":[{"i":{"x":0.833,"y":0.892},"o":{"x":0.167,"y":0.167},"t":0,"s":[790.51,237.439,0],"to":[0.07,-0.012,0],"ti":[-0.057,0.008,0]},{"i":{"x":0.833,"y":0.645},"o":{"x":0.167,"y":0.36},"t":1,"s":[790.932,237.369,0],"to":[0.057,-0.008,0],"ti":[0.078,-0.03,0]},{"i":{"x":0.833,"y":0.824},"o":{"x":0.167,"y":0.109},"t":2,"s":[790.854,237.392,0],"to":[-0.078,0.03,0],"ti":[0.136,-0.056,0]},{"i":{"x":0.833,"y":0.863},"o":{"x":0.167,"y":0.158},"t":3,"s":[790.464,237.55,0],"to":[-0.136,0.056,0],"ti":[0.117,-0.051,0]},{"i":{"x":0.833,"y":0.893},"o":{"x":0.167,"y":0.213},"t":4,"s":[790.035,237.731,0],"to":[-0.117,0.051,0],"ti":[0.044,-0.022,0]},{"i":{"x":0.833,"y":0.557},"o":{"x":0.167,"y":0.377},"t":5,"s":[789.763,237.854,0],"to":[-0.044,0.022,0],"ti":[-0.058,0.021,0]},{"i":{"x":0.833,"y":0.811},"o":{"x":0.167,"y":0.103},"t":6,"s":[789.771,237.862,0],"to":[0.058,-0.021,0],"ti":[-0.133,0.031,0]},{"i":{"x":0.833,"y":0.861},"o":{"x":0.167,"y":0.149},"t":7,"s":[790.111,237.73,0],"to":[0.133,-0.031,0],"ti":[-0.117,-0.02,0]},{"i":{"x":0.833,"y":0.84},"o":{"x":0.167,"y":0.207},"t":8,"s":[790.566,237.678,0],"to":[0.117,0.02,0],"ti":[-0.033,-0.074,0]},{"i":{"x":0.833,"y":0.802},"o":{"x":0.167,"y":0.174},"t":9,"s":[790.81,237.851,0],"to":[0.033,0.074,0],"ti":[0.058,-0.087,0]},{"i":{"x":0.833,"y":0.828},"o":{"x":0.167,"y":0.144},"t":10,"s":[790.763,238.122,0],"to":[-0.058,0.087,0],"ti":[0.116,-0.062,0]},{"i":{"x":0.833,"y":0.866},"o":{"x":0.167,"y":0.162},"t":11,"s":[790.463,238.373,0],"to":[-0.116,0.062,0],"ti":[0.104,-0.002,0]},{"i":{"x":0.833,"y":0.879},"o":{"x":0.167,"y":0.22},"t":12,"s":[790.064,238.494,0],"to":[-0.104,0.002,0],"ti":[0.046,0.034,0]},{"i":{"x":0.833,"y":0.834},"o":{"x":0.167,"y":0.266},"t":13,"s":[789.839,238.387,0],"to":[-0.046,-0.034,0],"ti":[0.022,0.004,0]},{"i":{"x":0.833,"y":0.83},"o":{"x":0.167,"y":0.167},"t":14,"s":[789.787,238.287,0],"to":[-0.022,-0.004,0],"ti":[0.026,-0.029,0]},{"i":{"x":0.833,"y":0.879},"o":{"x":0.167,"y":0.164},"t":15,"s":[789.704,238.364,0],"to":[-0.026,0.029,0],"ti":[0.019,-0.016,0]},{"i":{"x":0.833,"y":0.66},"o":{"x":0.167,"y":0.268},"t":16,"s":[789.631,238.459,0],"to":[-0.019,0.016,0],"ti":[0.005,0.028,0]},{"i":{"x":0.833,"y":0.737},"o":{"x":0.167,"y":0.11},"t":17,"s":[789.593,238.458,0],"to":[-0.005,-0.028,0],"ti":[-0.008,0.087,0]},{"i":{"x":0.833,"y":0.811},"o":{"x":0.167,"y":0.122},"t":18,"s":[789.599,238.292,0],"to":[0.008,-0.087,0],"ti":[-0.025,0.133,0]},{"i":{"x":0.833,"y":0.849},"o":{"x":0.167,"y":0.149},"t":19,"s":[789.642,237.935,0],"to":[0.025,-0.133,0],"ti":[-0.049,0.127,0]},{"i":{"x":0.833,"y":0.863},"o":{"x":0.167,"y":0.186},"t":20,"s":[789.752,237.494,0],"to":[0.049,-0.127,0],"ti":[-0.065,0.071,0]},{"i":{"x":0.833,"y":0.84},"o":{"x":0.167,"y":0.212},"t":21,"s":[789.935,237.175,0],"to":[0.065,-0.071,0],"ti":[-0.066,0.002,0]},{"i":{"x":0.833,"y":0.823},"o":{"x":0.167,"y":0.174},"t":22,"s":[790.142,237.068,0],"to":[0.066,-0.002,0],"ti":[-0.056,-0.05,0]},{"i":{"x":0.833,"y":0.873},"o":{"x":0.167,"y":0.158},"t":23,"s":[790.333,237.166,0],"to":[0.056,0.05,0],"ti":[-0.035,-0.051,0]},{"i":{"x":0.833,"y":0.85},"o":{"x":0.167,"y":0.244},"t":24,"s":[790.475,237.367,0],"to":[0.035,0.051,0],"ti":[-0.004,-0.033,0]},{"i":{"x":0.833,"y":0.726},"o":{"x":0.167,"y":0.187},"t":25,"s":[790.541,237.475,0],"to":[0.004,0.033,0],"ti":[0.029,-0.048,0]},{"i":{"x":0.833,"y":0.833},"o":{"x":0.167,"y":0.12},"t":26,"s":[790.501,237.566,0],"to":[-0.029,0.048,0],"ti":[0.051,-0.058,0]},{"i":{"x":0.833,"y":0.853},"o":{"x":0.167,"y":0.166},"t":27,"s":[790.37,237.761,0],"to":[-0.051,0.058,0],"ti":[0.058,-0.031,0]},{"i":{"x":0.833,"y":0.834},"o":{"x":0.167,"y":0.192},"t":28,"s":[790.194,237.917,0],"to":[-0.058,0.031,0],"ti":[0.05,0.014,0]},{"i":{"x":0.833,"y":0.801},"o":{"x":0.167,"y":0.168},"t":29,"s":[790.021,237.949,0],"to":[-0.05,-0.014,0],"ti":[0.026,0.06,0]},{"i":{"x":0.833,"y":0.81},"o":{"x":0.167,"y":0.143},"t":30,"s":[789.895,237.831,0],"to":[-0.026,-0.06,0],"ti":[-0.024,0.083,0]},{"i":{"x":0.833,"y":0.833},"o":{"x":0.167,"y":0.149},"t":31,"s":[789.862,237.589,0],"to":[0.024,-0.083,0],"ti":[-0.073,0.074,0]},{"i":{"x":0.833,"y":0.881},"o":{"x":0.167,"y":0.167},"t":32,"s":[790.041,237.33,0],"to":[0.073,-0.074,0],"ti":[-0.061,0.044,0]},{"i":{"x":0.833,"y":0.823},"o":{"x":0.167,"y":0.275},"t":33,"s":[790.301,237.148,0],"to":[0.061,-0.044,0],"ti":[0.008,0.012,0]},{"i":{"x":0.833,"y":0.698},"o":{"x":0.167,"y":0.157},"t":34,"s":[790.409,237.067,0],"to":[-0.008,-0.012,0],"ti":[0.093,-0.007,0]},{"i":{"x":0.833,"y":0.809},"o":{"x":0.167,"y":0.115},"t":35,"s":[790.256,237.073,0],"to":[-0.093,0.007,0],"ti":[0.155,-0.002,0]},{"i":{"x":0.833,"y":0.841},"o":{"x":0.167,"y":0.148},"t":36,"s":[789.85,237.111,0],"to":[-0.155,0.002,0],"ti":[0.167,-0.003,0]},{"i":{"x":0.833,"y":0.844},"o":{"x":0.167,"y":0.175},"t":37,"s":[789.324,237.084,0],"to":[-0.167,0.003,0],"ti":[0.134,-0.049,0]},{"i":{"x":0.833,"y":0.839},"o":{"x":0.167,"y":0.178},"t":38,"s":[788.849,237.127,0],"to":[-0.134,0.049,0],"ti":[0.079,-0.102,0]},{"i":{"x":0.833,"y":0.837},"o":{"x":0.167,"y":0.172},"t":39,"s":[788.519,237.379,0],"to":[-0.079,0.102,0],"ti":[0.021,-0.122,0]},{"i":{"x":0.833,"y":0.854},"o":{"x":0.167,"y":0.171},"t":40,"s":[788.377,237.741,0],"to":[-0.021,0.122,0],"ti":[-0.014,-0.108,0]},{"i":{"x":0.833,"y":0.886},"o":{"x":0.167,"y":0.193},"t":41,"s":[788.393,238.113,0],"to":[0.014,0.108,0],"ti":[-0.002,-0.056,0]},{"i":{"x":0.833,"y":0.762},"o":{"x":0.167,"y":0.31},"t":42,"s":[788.462,238.388,0],"to":[0.002,0.056,0],"ti":[0.029,0.014,0]},{"i":{"x":0.833,"y":0.799},"o":{"x":0.167,"y":0.128},"t":43,"s":[788.406,238.452,0],"to":[-0.029,-0.014,0],"ti":[0.015,0.069,0]},{"i":{"x":0.833,"y":0.795},"o":{"x":0.167,"y":0.142},"t":44,"s":[788.287,238.306,0],"to":[-0.015,-0.069,0],"ti":[-0.035,0.103,0]},{"i":{"x":0.833,"y":0.833},"o":{"x":0.167,"y":0.141},"t":45,"s":[788.317,238.038,0],"to":[0.035,-0.103,0],"ti":[-0.03,0.059,0]},{"t":46.0000018736184,"s":[788.5,237.685,0]}],"ix":2},"a":{"a":0,"k":[0,0,0],"ix":1},"s":{"a":0,"k":[100,100,100],"ix":6}},"ao":0,"shapes":[{"ty":"gr","it":[{"d":1,"ty":"el","s":{"a":0,"k":[195.234,195.234],"ix":2},"p":{"a":0,"k":[0,0],"ix":3},"nm":"Ellipse Path 1","mn":"ADBE Vector Shape - Ellipse","hd":false},{"ty":"tr","p":{"a":1,"k":[{"i":{"x":0,"y":1},"o":{"x":0.167,"y":0.167},"t":12,"s":[-65.883,-28.258],"to":[-72.75,6.773],"ti":[72.75,-6.773]},{"t":59.6125024280669,"s":[-502.383,12.383]}],"ix":2},"a":{"a":0,"k":[0,0],"ix":1},"s":{"a":1,"k":[{"i":{"x":[0,0],"y":[1,1]},"o":{"x":[0.167,0.167],"y":[0.167,0.167]},"t":12,"s":[0,0]},{"t":27.0000010997325,"s":[100,100]}],"ix":3},"r":{"a":0,"k":0,"ix":6},"o":{"a":0,"k":100,"ix":7},"sk":{"a":0,"k":0,"ix":4},"sa":{"a":0,"k":0,"ix":5},"nm":"Transform"}],"nm":"Ellipse 6","np":1,"cix":2,"bm":0,"ix":1,"mn":"ADBE Vector Group","hd":false},{"ty":"gr","it":[{"d":1,"ty":"el","s":{"a":0,"k":[78.625,71.023],"ix":2},"p":{"a":0,"k":[0,0],"ix":3},"nm":"Ellipse Path 1","mn":"ADBE Vector Shape - Ellipse","hd":false},{"ty":"tr","p":{"a":1,"k":[{"i":{"x":0,"y":1},"o":{"x":0.167,"y":0.167},"t":12,"s":[-59.914,-25.348],"to":[-0.984,39.152],"ti":[0.984,-39.152]},{"t":59.0000024031193,"s":[-65.82,209.566]}],"ix":2},"a":{"a":0,"k":[0,0],"ix":1},"s":{"a":1,"k":[{"i":{"x":[0,0],"y":[1,1]},"o":{"x":[0.167,0.167],"y":[0.167,0.167]},"t":12,"s":[0,0]},{"t":27.0000010997325,"s":[100,100]}],"ix":3},"r":{"a":0,"k":0,"ix":6},"o":{"a":0,"k":100,"ix":7},"sk":{"a":0,"k":0,"ix":4},"sa":{"a":0,"k":0,"ix":5},"nm":"Transform"}],"nm":"Ellipse 5","np":1,"cix":2,"bm":0,"ix":2,"mn":"ADBE Vector Group","hd":false},{"ty":"gr","it":[{"d":1,"ty":"el","s":{"a":0,"k":[169.391,169.391],"ix":2},"p":{"a":0,"k":[0,0],"ix":3},"nm":"Ellipse Path 1","mn":"ADBE Vector Shape - Ellipse","hd":false},{"ty":"tr","p":{"a":1,"k":[{"i":{"x":0,"y":1},"o":{"x":0.167,"y":0.167},"t":12,"s":[-70.266,-26.227],"to":[53.928,13.589],"ti":[-53.928,-13.589]},{"t":59.6125024280669,"s":[253.305,55.305]}],"ix":2},"a":{"a":0,"k":[0,0],"ix":1},"s":{"a":1,"k":[{"i":{"x":[0,0],"y":[1,1]},"o":{"x":[0.167,0.167],"y":[0.167,0.167]},"t":12,"s":[0,0]},{"t":27.0000010997325,"s":[100,100]}],"ix":3},"r":{"a":0,"k":0,"ix":6},"o":{"a":0,"k":100,"ix":7},"sk":{"a":0,"k":0,"ix":4},"sa":{"a":0,"k":0,"ix":5},"nm":"Transform"}],"nm":"Ellipse 4","np":1,"cix":2,"bm":0,"ix":3,"mn":"ADBE Vector Group","hd":false},{"ty":"gr","it":[{"d":1,"ty":"el","s":{"a":0,"k":[85.172,85.172],"ix":2},"p":{"a":0,"k":[0,0],"ix":3},"nm":"Ellipse Path 1","mn":"ADBE Vector Shape - Ellipse","hd":false},{"ty":"tr","p":{"a":1,"k":[{"i":{"x":0,"y":1},"o":{"x":0.167,"y":0.167},"t":12,"s":[-58.273,-22.297],"to":[81.948,-5.52],"ti":[-81.948,5.52]},{"t":59.6125024280669,"s":[433.414,-55.414]}],"ix":2},"a":{"a":0,"k":[0,0],"ix":1},"s":{"a":1,"k":[{"i":{"x":[0,0],"y":[1,1]},"o":{"x":[0.167,0.167],"y":[0.167,0.167]},"t":12,"s":[0,0]},{"t":27.0000010997325,"s":[100,100]}],"ix":3},"r":{"a":0,"k":0,"ix":6},"o":{"a":0,"k":100,"ix":7},"sk":{"a":0,"k":0,"ix":4},"sa":{"a":0,"k":0,"ix":5},"nm":"Transform"}],"nm":"Ellipse 3","np":1,"cix":2,"bm":0,"ix":4,"mn":"ADBE Vector Group","hd":false},{"ty":"gr","it":[{"d":1,"ty":"el","s":{"a":0,"k":[160.367,157.07],"ix":2},"p":{"a":0,"k":[0,0],"ix":3},"nm":"Ellipse Path 1","mn":"ADBE Vector Shape - Ellipse","hd":false},{"ty":"tr","p":{"a":1,"k":[{"i":{"x":0,"y":1},"o":{"x":0.167,"y":0.167},"t":12,"s":[-59.926,-25.91],"to":[-4.315,-20.592],"ti":[4.315,20.592]},{"t":59.6125024280669,"s":[-85.816,-149.465]}],"ix":2},"a":{"a":0,"k":[0,0],"ix":1},"s":{"a":1,"k":[{"i":{"x":[0,0],"y":[1,1]},"o":{"x":[0.167,0.167],"y":[0.167,0.167]},"t":12,"s":[0,0]},{"t":27.0000010997325,"s":[100,100]}],"ix":3},"r":{"a":0,"k":0,"ix":6},"o":{"a":0,"k":100,"ix":7},"sk":{"a":0,"k":0,"ix":4},"sa":{"a":0,"k":0,"ix":5},"nm":"Transform"}],"nm":"Ellipse 2","np":1,"cix":2,"bm":0,"ix":5,"mn":"ADBE Vector Group","hd":false},{"ty":"gr","it":[{"d":1,"ty":"el","s":{"a":0,"k":[99.898,99.898],"ix":2},"p":{"a":0,"k":[0,0],"ix":3},"nm":"Ellipse Path 1","mn":"ADBE Vector Shape - Ellipse","hd":false},{"ty":"tr","p":{"a":1,"k":[{"i":{"x":0,"y":1},"o":{"x":0.167,"y":0.167},"t":12,"s":[-61.262,-21.645],"to":[-48.465,-22.068],"ti":[48.465,22.068]},{"t":59.6125024280669,"s":[-352.051,-154.051]}],"ix":2},"a":{"a":0,"k":[0,0],"ix":1},"s":{"a":1,"k":[{"i":{"x":[0,0],"y":[1,1]},"o":{"x":[0.167,0.167],"y":[0.167,0.167]},"t":12,"s":[0,0]},{"t":27.0000010997325,"s":[100,100]}],"ix":3},"r":{"a":0,"k":0,"ix":6},"o":{"a":0,"k":100,"ix":7},"sk":{"a":0,"k":0,"ix":4},"sa":{"a":0,"k":0,"ix":5},"nm":"Transform"}],"nm":"Ellipse 1","np":1,"cix":2,"bm":0,"ix":6,"mn":"ADBE Vector Group","hd":false},{"ty":"st","c":{"a":0,"k":[0.113332368433,0.648817241192,0.966344952583,1],"ix":3},"o":{"a":0,"k":99,"ix":4},"w":{"a":0,"k":26,"ix":5},"lc":1,"lj":1,"ml":4,"bm":0,"nm":"Stroke 1","mn":"ADBE Vector Graphic - Stroke","hd":false}],"ip":0,"op":47.0000019143492,"st":0,"bm":0},{"ddd":0,"ind":4,"ty":4,"nm":"Shape Layer 6","sr":1,"ks":{"o":{"a":1,"k":[{"i":{"x":[0.833],"y":[0.833]},"o":{"x":[0.167],"y":[0.167]},"t":41,"s":[40]},{"t":45.0000018328876,"s":[0]}],"ix":11},"r":{"a":0,"k":0,"ix":10},"p":{"a":1,"k":[{"i":{"x":0.833,"y":0.828},"o":{"x":0.167,"y":0.167},"t":0,"s":[799.516,249.958,0],"to":[0.028,0.049,0],"ti":[-0.081,-0.076,0]},{"i":{"x":0.833,"y":0.815},"o":{"x":0.167,"y":0.162},"t":1,"s":[799.683,250.254,0],"to":[0.081,0.076,0],"ti":[-0.124,-0.01,0]},{"i":{"x":0.833,"y":0.808},"o":{"x":0.167,"y":0.152},"t":2,"s":[800.002,250.412,0],"to":[0.124,0.01,0],"ti":[-0.139,0.084,0]},{"i":{"x":0.833,"y":0.863},"o":{"x":0.167,"y":0.147},"t":3,"s":[800.427,250.315,0],"to":[0.139,-0.084,0],"ti":[-0.117,0.106,0]},{"i":{"x":0.833,"y":0.859},"o":{"x":0.167,"y":0.212},"t":4,"s":[800.838,249.909,0],"to":[0.117,-0.106,0],"ti":[-0.068,0.004,0]},{"i":{"x":0.833,"y":0.772},"o":{"x":0.167,"y":0.203},"t":5,"s":[801.129,249.681,0],"to":[0.068,-0.004,0],"ti":[-0.007,-0.108,0]},{"i":{"x":0.833,"y":0.822},"o":{"x":0.167,"y":0.131},"t":6,"s":[801.246,249.888,0],"to":[0.007,0.108,0],"ti":[0.05,-0.151,0]},{"i":{"x":0.833,"y":0.858},"o":{"x":0.167,"y":0.156},"t":7,"s":[801.169,250.331,0],"to":[-0.05,0.151,0],"ti":[0.079,-0.119,0]},{"i":{"x":0.833,"y":0.861},"o":{"x":0.167,"y":0.202},"t":8,"s":[800.945,250.794,0],"to":[-0.079,0.119,0],"ti":[0.057,-0.007,0]},{"i":{"x":0.833,"y":0.781},"o":{"x":0.167,"y":0.208},"t":9,"s":[800.694,251.045,0],"to":[-0.057,0.007,0],"ti":[0.025,0.099,0]},{"i":{"x":0.833,"y":0.849},"o":{"x":0.167,"y":0.135},"t":10,"s":[800.602,250.838,0],"to":[-0.025,-0.099,0],"ti":[0.045,0.102,0]},{"i":{"x":0.833,"y":0.827},"o":{"x":0.167,"y":0.186},"t":11,"s":[800.545,250.452,0],"to":[-0.045,-0.102,0],"ti":[0.089,0.054,0]},{"i":{"x":0.833,"y":0.827},"o":{"x":0.167,"y":0.161},"t":12,"s":[800.333,250.226,0],"to":[-0.089,-0.054,0],"ti":[0.114,0.021,0]},{"i":{"x":0.833,"y":0.843},"o":{"x":0.167,"y":0.161},"t":13,"s":[800.01,250.129,0],"to":[-0.114,-0.021,0],"ti":[0.113,0.014,0]},{"i":{"x":0.833,"y":0.845},"o":{"x":0.167,"y":0.178},"t":14,"s":[799.646,250.1,0],"to":[-0.113,-0.014,0],"ti":[0.079,0.045,0]},{"i":{"x":0.833,"y":0.801},"o":{"x":0.167,"y":0.181},"t":15,"s":[799.331,250.043,0],"to":[-0.079,-0.045,0],"ti":[0.009,0.097,0]},{"i":{"x":0.833,"y":0.827},"o":{"x":0.167,"y":0.143},"t":16,"s":[799.175,249.827,0],"to":[-0.009,-0.097,0],"ti":[-0.06,0.114,0]},{"i":{"x":0.833,"y":0.849},"o":{"x":0.167,"y":0.161},"t":17,"s":[799.275,249.461,0],"to":[0.06,-0.114,0],"ti":[-0.092,0.081,0]},{"i":{"x":0.833,"y":0.861},"o":{"x":0.167,"y":0.186},"t":18,"s":[799.534,249.143,0],"to":[0.092,-0.081,0],"ti":[-0.085,0.026,0]},{"i":{"x":0.833,"y":0.858},"o":{"x":0.167,"y":0.208},"t":19,"s":[799.824,248.977,0],"to":[0.085,-0.026,0],"ti":[-0.049,-0.023,0]},{"i":{"x":0.833,"y":0.836},"o":{"x":0.167,"y":0.202},"t":20,"s":[800.043,248.987,0],"to":[0.049,0.023,0],"ti":[0.005,-0.039,0]},{"i":{"x":0.833,"y":0.714},"o":{"x":0.167,"y":0.169},"t":21,"s":[800.121,249.114,0],"to":[-0.005,0.039,0],"ti":[0.064,-0.058,0]},{"i":{"x":0.833,"y":0.809},"o":{"x":0.167,"y":0.118},"t":22,"s":[800.016,249.22,0],"to":[-0.064,0.058,0],"ti":[0.098,-0.102,0]},{"i":{"x":0.833,"y":0.858},"o":{"x":0.167,"y":0.148},"t":23,"s":[799.736,249.464,0],"to":[-0.098,0.102,0],"ti":[0.088,-0.104,0]},{"i":{"x":0.833,"y":0.893},"o":{"x":0.167,"y":0.202},"t":24,"s":[799.426,249.83,0],"to":[-0.088,0.104,0],"ti":[0.046,-0.048,0]},{"i":{"x":0.833,"y":0.71},"o":{"x":0.167,"y":0.376},"t":25,"s":[799.211,250.09,0],"to":[-0.046,0.048,0],"ti":[-0.002,0.033,0]},{"i":{"x":0.833,"y":0.77},"o":{"x":0.167,"y":0.117},"t":26,"s":[799.148,250.118,0],"to":[0.002,-0.033,0],"ti":[-0.035,0.103,0]},{"i":{"x":0.833,"y":0.81},"o":{"x":0.167,"y":0.131},"t":27,"s":[799.223,249.893,0],"to":[0.035,-0.103,0],"ti":[-0.088,0.125,0]},{"i":{"x":0.833,"y":0.829},"o":{"x":0.167,"y":0.149},"t":28,"s":[799.358,249.5,0],"to":[0.088,-0.125,0],"ti":[-0.152,0.093,0]},{"i":{"x":0.833,"y":0.868},"o":{"x":0.167,"y":0.163},"t":29,"s":[799.75,249.143,0],"to":[0.152,-0.093,0],"ti":[-0.14,0.039,0]},{"i":{"x":0.833,"y":0.882},"o":{"x":0.167,"y":0.227},"t":30,"s":[800.27,248.941,0],"to":[0.14,-0.039,0],"ti":[-0.046,-0.008,0]},{"i":{"x":0.833,"y":0.658},"o":{"x":0.167,"y":0.282},"t":31,"s":[800.59,248.907,0],"to":[0.046,0.008,0],"ti":[0.075,-0.031,0]},{"i":{"x":0.833,"y":0.796},"o":{"x":0.167,"y":0.11},"t":32,"s":[800.546,248.992,0],"to":[-0.075,0.031,0],"ti":[0.168,-0.009,0]},{"i":{"x":0.833,"y":0.837},"o":{"x":0.167,"y":0.141},"t":33,"s":[800.139,249.091,0],"to":[-0.168,0.009,0],"ti":[0.192,-0.018,0]},{"i":{"x":0.833,"y":0.837},"o":{"x":0.167,"y":0.171},"t":34,"s":[799.535,249.044,0],"to":[-0.192,0.018,0],"ti":[0.145,-0.1,0]},{"i":{"x":0.833,"y":0.847},"o":{"x":0.167,"y":0.17},"t":35,"s":[798.985,249.199,0],"to":[-0.145,0.1,0],"ti":[0.057,-0.15,0]},{"i":{"x":0.833,"y":0.851},"o":{"x":0.167,"y":0.183},"t":36,"s":[798.665,249.644,0],"to":[-0.057,0.15,0],"ti":[-0.035,-0.122,0]},{"i":{"x":0.833,"y":0.843},"o":{"x":0.167,"y":0.189},"t":37,"s":[798.644,250.102,0],"to":[0.035,0.122,0],"ti":[-0.09,-0.041,0]},{"i":{"x":0.833,"y":0.815},"o":{"x":0.167,"y":0.177},"t":38,"s":[798.874,250.377,0],"to":[0.09,0.041,0],"ti":[-0.068,0.067,0]},{"i":{"x":0.833,"y":0.798},"o":{"x":0.167,"y":0.151},"t":39,"s":[799.183,250.347,0],"to":[0.068,-0.067,0],"ti":[0.023,0.148,0]},{"i":{"x":0.833,"y":0.838},"o":{"x":0.167,"y":0.142},"t":40,"s":[799.283,249.973,0],"to":[-0.023,-0.148,0],"ti":[0.097,0.153,0]},{"i":{"x":0.833,"y":0.861},"o":{"x":0.167,"y":0.172},"t":41,"s":[799.044,249.462,0],"to":[-0.097,-0.153,0],"ti":[0.103,0.106,0]},{"i":{"x":0.833,"y":0.888},"o":{"x":0.167,"y":0.207},"t":42,"s":[798.7,249.054,0],"to":[-0.103,-0.106,0],"ti":[0.064,0.047,0]},{"i":{"x":0.833,"y":0.856},"o":{"x":0.167,"y":0.325},"t":43,"s":[798.424,248.827,0],"to":[-0.064,-0.047,0],"ti":[0.005,0.004,0]},{"i":{"x":0.833,"y":0.706},"o":{"x":0.167,"y":0.198},"t":44,"s":[798.314,248.773,0],"to":[-0.005,-0.004,0],"ti":[-0.05,0.004,0]},{"i":{"x":0.833,"y":0.833},"o":{"x":0.167,"y":0.116},"t":45,"s":[798.394,248.804,0],"to":[0.05,-0.004,0],"ti":[-0.037,0.009,0]},{"t":46.0000018736184,"s":[798.616,248.751,0]}],"ix":2},"a":{"a":0,"k":[0,0,0],"ix":1},"s":{"a":0,"k":[100,100,100],"ix":6}},"ao":0,"shapes":[{"ty":"gr","it":[{"d":1,"ty":"el","s":{"a":0,"k":[195.234,195.234],"ix":2},"p":{"a":0,"k":[0,0],"ix":3},"nm":"Ellipse Path 1","mn":"ADBE Vector Shape - Ellipse","hd":false},{"ty":"tr","p":{"a":1,"k":[{"i":{"x":0,"y":1},"o":{"x":0.167,"y":0.167},"t":12,"s":[-65.883,-28.258],"to":[-72.75,6.773],"ti":[72.75,-6.773]},{"t":59.6125024280669,"s":[-502.383,12.383]}],"ix":2},"a":{"a":0,"k":[0,0],"ix":1},"s":{"a":1,"k":[{"i":{"x":[0,0],"y":[1,1]},"o":{"x":[0.167,0.167],"y":[0.167,0.167]},"t":12,"s":[0,0]},{"t":27.0000010997325,"s":[100,100]}],"ix":3},"r":{"a":0,"k":0,"ix":6},"o":{"a":0,"k":100,"ix":7},"sk":{"a":0,"k":0,"ix":4},"sa":{"a":0,"k":0,"ix":5},"nm":"Transform"}],"nm":"Ellipse 6","np":1,"cix":2,"bm":0,"ix":1,"mn":"ADBE Vector Group","hd":false},{"ty":"gr","it":[{"d":1,"ty":"el","s":{"a":0,"k":[78.625,71.023],"ix":2},"p":{"a":0,"k":[0,0],"ix":3},"nm":"Ellipse Path 1","mn":"ADBE Vector Shape - Ellipse","hd":false},{"ty":"tr","p":{"a":1,"k":[{"i":{"x":0,"y":1},"o":{"x":0.167,"y":0.167},"t":12,"s":[-59.914,-25.348],"to":[-0.984,39.152],"ti":[0.984,-39.152]},{"t":59.0000024031193,"s":[-65.82,209.566]}],"ix":2},"a":{"a":0,"k":[0,0],"ix":1},"s":{"a":1,"k":[{"i":{"x":[0,0],"y":[1,1]},"o":{"x":[0.167,0.167],"y":[0.167,0.167]},"t":12,"s":[0,0]},{"t":27.0000010997325,"s":[100,100]}],"ix":3},"r":{"a":0,"k":0,"ix":6},"o":{"a":0,"k":100,"ix":7},"sk":{"a":0,"k":0,"ix":4},"sa":{"a":0,"k":0,"ix":5},"nm":"Transform"}],"nm":"Ellipse 5","np":1,"cix":2,"bm":0,"ix":2,"mn":"ADBE Vector Group","hd":false},{"ty":"gr","it":[{"d":1,"ty":"el","s":{"a":0,"k":[169.391,169.391],"ix":2},"p":{"a":0,"k":[0,0],"ix":3},"nm":"Ellipse Path 1","mn":"ADBE Vector Shape - Ellipse","hd":false},{"ty":"tr","p":{"a":1,"k":[{"i":{"x":0,"y":1},"o":{"x":0.167,"y":0.167},"t":12,"s":[-70.266,-26.227],"to":[53.928,13.589],"ti":[-53.928,-13.589]},{"t":59.6125024280669,"s":[253.305,55.305]}],"ix":2},"a":{"a":0,"k":[0,0],"ix":1},"s":{"a":1,"k":[{"i":{"x":[0,0],"y":[1,1]},"o":{"x":[0.167,0.167],"y":[0.167,0.167]},"t":12,"s":[0,0]},{"t":27.0000010997325,"s":[100,100]}],"ix":3},"r":{"a":0,"k":0,"ix":6},"o":{"a":0,"k":100,"ix":7},"sk":{"a":0,"k":0,"ix":4},"sa":{"a":0,"k":0,"ix":5},"nm":"Transform"}],"nm":"Ellipse 4","np":1,"cix":2,"bm":0,"ix":3,"mn":"ADBE Vector Group","hd":false},{"ty":"gr","it":[{"d":1,"ty":"el","s":{"a":0,"k":[85.172,85.172],"ix":2},"p":{"a":0,"k":[0,0],"ix":3},"nm":"Ellipse Path 1","mn":"ADBE Vector Shape - Ellipse","hd":false},{"ty":"tr","p":{"a":1,"k":[{"i":{"x":0,"y":1},"o":{"x":0.167,"y":0.167},"t":12,"s":[-58.273,-22.297],"to":[81.948,-5.52],"ti":[-81.948,5.52]},{"t":59.6125024280669,"s":[433.414,-55.414]}],"ix":2},"a":{"a":0,"k":[0,0],"ix":1},"s":{"a":1,"k":[{"i":{"x":[0,0],"y":[1,1]},"o":{"x":[0.167,0.167],"y":[0.167,0.167]},"t":12,"s":[0,0]},{"t":27.0000010997325,"s":[100,100]}],"ix":3},"r":{"a":0,"k":0,"ix":6},"o":{"a":0,"k":100,"ix":7},"sk":{"a":0,"k":0,"ix":4},"sa":{"a":0,"k":0,"ix":5},"nm":"Transform"}],"nm":"Ellipse 3","np":1,"cix":2,"bm":0,"ix":4,"mn":"ADBE Vector Group","hd":false},{"ty":"gr","it":[{"d":1,"ty":"el","s":{"a":0,"k":[160.367,157.07],"ix":2},"p":{"a":0,"k":[0,0],"ix":3},"nm":"Ellipse Path 1","mn":"ADBE Vector Shape - Ellipse","hd":false},{"ty":"tr","p":{"a":1,"k":[{"i":{"x":0,"y":1},"o":{"x":0.167,"y":0.167},"t":12,"s":[-59.926,-25.91],"to":[-4.315,-20.592],"ti":[4.315,20.592]},{"t":59.6125024280669,"s":[-85.816,-149.465]}],"ix":2},"a":{"a":0,"k":[0,0],"ix":1},"s":{"a":1,"k":[{"i":{"x":[0,0],"y":[1,1]},"o":{"x":[0.167,0.167],"y":[0.167,0.167]},"t":12,"s":[0,0]},{"t":27.0000010997325,"s":[100,100]}],"ix":3},"r":{"a":0,"k":0,"ix":6},"o":{"a":0,"k":100,"ix":7},"sk":{"a":0,"k":0,"ix":4},"sa":{"a":0,"k":0,"ix":5},"nm":"Transform"}],"nm":"Ellipse 2","np":1,"cix":2,"bm":0,"ix":5,"mn":"ADBE Vector Group","hd":false},{"ty":"gr","it":[{"d":1,"ty":"el","s":{"a":0,"k":[99.898,99.898],"ix":2},"p":{"a":0,"k":[0,0],"ix":3},"nm":"Ellipse Path 1","mn":"ADBE Vector Shape - Ellipse","hd":false},{"ty":"tr","p":{"a":1,"k":[{"i":{"x":0,"y":1},"o":{"x":0.167,"y":0.167},"t":12,"s":[-61.262,-21.645],"to":[-48.465,-22.068],"ti":[48.465,22.068]},{"t":59.6125024280669,"s":[-352.051,-154.051]}],"ix":2},"a":{"a":0,"k":[0,0],"ix":1},"s":{"a":1,"k":[{"i":{"x":[0,0],"y":[1,1]},"o":{"x":[0.167,0.167],"y":[0.167,0.167]},"t":12,"s":[0,0]},{"t":27.0000010997325,"s":[100,100]}],"ix":3},"r":{"a":0,"k":0,"ix":6},"o":{"a":0,"k":100,"ix":7},"sk":{"a":0,"k":0,"ix":4},"sa":{"a":0,"k":0,"ix":5},"nm":"Transform"}],"nm":"Ellipse 1","np":1,"cix":2,"bm":0,"ix":6,"mn":"ADBE Vector Group","hd":false},{"ty":"st","c":{"a":0,"k":[0.278010379567,0.296622721354,0.307659313725,1],"ix":3},"o":{"a":0,"k":69,"ix":4},"w":{"a":0,"k":26,"ix":5},"lc":1,"lj":1,"ml":4,"bm":0,"nm":"Stroke 1","mn":"ADBE Vector Graphic - Stroke","hd":false}],"ip":0,"op":47.0000019143492,"st":0,"bm":0},{"ddd":0,"ind":5,"ty":5,"nm":"BUTTON ","sr":1,"ks":{"o":{"a":0,"k":100,"ix":11},"r":{"a":0,"k":0,"ix":10},"p":{"a":0,"k":[728.867,226.911,0],"ix":2},"a":{"a":0,"k":[0,-61.089,0],"ix":1},"s":{"a":0,"k":[100,100,100],"ix":6}},"ao":0,"t":{"d":{"k":[{"s":{"s":180,"f":"MyriadPro-Semibold","t":"BUTTON","j":2,"tr":0,"lh":216,"ls":0,"fc":[0.192,0.133,0.549]},"t":0}]},"p":{},"m":{"g":1,"a":{"a":0,"k":[0,0],"ix":2}},"a":[]},"ip":0,"op":47.0000019143492,"st":0,"bm":0},{"ddd":0,"ind":6,"ty":4,"nm":"Shape Layer 2","sr":1,"ks":{"o":{"a":1,"k":[{"i":{"x":[0.833],"y":[0.833]},"o":{"x":[0.167],"y":[0.167]},"t":12,"s":[2]},{"t":20.0000008146167,"s":[100]}],"ix":11},"r":{"a":0,"k":0,"ix":10},"p":{"a":0,"k":[750,250,0],"ix":2},"a":{"a":0,"k":[0,0,0],"ix":1},"s":{"a":0,"k":[100,100,100],"ix":6}},"ao":0,"shapes":[{"ty":"gr","it":[{"ty":"rc","d":1,"s":{"a":0,"k":[905.734,267.484],"ix":2},"p":{"a":0,"k":[0,0],"ix":3},"r":{"a":0,"k":89,"ix":4},"nm":"Rectangle Path 1","mn":"ADBE Vector Shape - Rect","hd":false},{"ty":"fl","c":{"a":0,"k":[0.945358455181,0.633736133575,0.536673426628,1],"ix":4},"o":{"a":0,"k":100,"ix":5},"r":1,"bm":0,"nm":"Fill 1","mn":"ADBE Vector Graphic - Fill","hd":false},{"ty":"tr","p":{"a":0,"k":[-29.133,-24.258],"ix":2},"a":{"a":0,"k":[0,0],"ix":1},"s":{"a":0,"k":[100,100],"ix":3},"r":{"a":0,"k":0,"ix":6},"o":{"a":0,"k":100,"ix":7},"sk":{"a":0,"k":0,"ix":4},"sa":{"a":0,"k":0,"ix":5},"nm":"Transform"}],"nm":"Rectangle 1","np":3,"cix":2,"bm":0,"ix":1,"mn":"ADBE Vector Group","hd":false}],"ip":12.00000048877,"op":47.0000019143492,"st":0,"bm":0},{"ddd":0,"ind":7,"ty":4,"nm":"Shape Layer 1","sr":1,"ks":{"o":{"a":0,"k":100,"ix":11},"r":{"a":0,"k":0,"ix":10},"p":{"a":0,"k":[750,250,0],"ix":2},"a":{"a":0,"k":[0,0,0],"ix":1},"s":{"a":0,"k":[100,100,100],"ix":6}},"ao":0,"shapes":[{"ty":"gr","it":[{"ty":"rc","d":1,"s":{"a":0,"k":[905.734,267.484],"ix":2},"p":{"a":0,"k":[0,0],"ix":3},"r":{"a":0,"k":89,"ix":4},"nm":"Rectangle Path 1","mn":"ADBE Vector Shape - Rect","hd":false},{"ty":"fl","c":{"a":0,"k":[0.945358455882,0.884093280867,0.53667345234,1],"ix":4},"o":{"a":0,"k":100,"ix":5},"r":1,"bm":0,"nm":"Fill 1","mn":"ADBE Vector Graphic - Fill","hd":false},{"ty":"tr","p":{"a":0,"k":[-29.133,-24.258],"ix":2},"a":{"a":0,"k":[0,0],"ix":1},"s":{"a":0,"k":[100,100],"ix":3},"r":{"a":0,"k":0,"ix":6},"o":{"a":0,"k":100,"ix":7},"sk":{"a":0,"k":0,"ix":4},"sa":{"a":0,"k":0,"ix":5},"nm":"Transform"}],"nm":"Rectangle 1","np":3,"cix":2,"bm":0,"ix":1,"mn":"ADBE Vector Group","hd":false}],"ip":0,"op":47.0000019143492,"st":0,"bm":0},{"ddd":0,"ind":8,"ty":4,"nm":"Shape Layer 3","sr":1,"ks":{"o":{"a":0,"k":100,"ix":11},"r":{"a":0,"k":0,"ix":10},"p":{"a":1,"k":[{"i":{"x":0.833,"y":0.833},"o":{"x":0.167,"y":0.167},"t":12,"s":[800.513,260.239,0],"to":[1.581,1.627,0],"ti":[-1.581,-1.627,0]},{"t":20.0000008146167,"s":[810,270,0]}],"ix":2},"a":{"a":0,"k":[0,0,0],"ix":1},"s":{"a":0,"k":[100,100,100],"ix":6}},"ao":0,"shapes":[{"ty":"gr","it":[{"ty":"rc","d":1,"s":{"a":0,"k":[905.734,267.484],"ix":2},"p":{"a":0,"k":[0,0],"ix":3},"r":{"a":0,"k":89,"ix":4},"nm":"Rectangle Path 1","mn":"ADBE Vector Shape - Rect","hd":false},{"ty":"fl","c":{"a":0,"k":[0.479212611914,0.479212611914,0.479212611914,1],"ix":4},"o":{"a":0,"k":100,"ix":5},"r":1,"bm":0,"nm":"Fill 1","mn":"ADBE Vector Graphic - Fill","hd":false},{"ty":"tr","p":{"a":0,"k":[-80.273,-35.461],"ix":2},"a":{"a":0,"k":[0,0],"ix":1},"s":{"a":0,"k":[100,100],"ix":3},"r":{"a":0,"k":0,"ix":6},"o":{"a":0,"k":100,"ix":7},"sk":{"a":0,"k":0,"ix":4},"sa":{"a":0,"k":0,"ix":5},"nm":"Transform"}],"nm":"Rectangle 1","np":3,"cix":2,"bm":0,"ix":1,"mn":"ADBE Vector Group","hd":false}],"ip":12.00000048877,"op":47.0000019143492,"st":0,"bm":0}],"markers":[],"chars":[{"ch":"B","size":180,"style":"Semibold","w":57.6,"data":{"shapes":[{"ty":"gr","it":[{"ind":0,"ty":"sh","ix":1,"ks":{"a":0,"k":{"i":[[0,0],[-6.848,0],[-4.834,4.23],[0,6.042],[7.15,1.813],[0,0],[0,6.244],[4.23,2.518],[9.164,0],[3.928,-0.806]],"o":[[3.122,0.403],[12.387,0],[3.928,-3.223],[0,-9.366],[0,0],[7.352,-2.719],[0,-5.74],[-4.633,-3.223],[-6.949,0],[0,0]],"v":[[7.15,-0.201],[22.357,0.705],[47.534,-5.64],[54.08,-19.638],[40.384,-36.456],[40.384,-36.658],[51.663,-51.361],[44.614,-64.05],[25.177,-68.381],[7.15,-66.971]],"c":true},"ix":2},"nm":"B","mn":"ADBE Vector Shape - Group","hd":false},{"ind":1,"ty":"sh","ix":2,"ks":{"a":0,"k":{"i":[[0,0],[-3.625,0],[0,-6.345],[8.56,0],[0,0]],"o":[[1.309,-0.302],[7.855,0],[0,5.74],[0,0],[0,0]],"v":[[19.437,-58.713],[26.486,-59.216],[39.175,-49.951],[25.781,-40.182],[19.437,-40.182]],"c":true},"ix":2},"nm":"B","mn":"ADBE Vector Shape - Group","hd":false},{"ind":2,"ty":"sh","ix":3,"ks":{"a":0,"k":{"i":[[0,0],[0,0],[0,-7.855],[7.956,0],[1.611,0.201]],"o":[[0,0],[8.56,0],[0,8.359],[-2.82,0],[0,0]],"v":[[19.437,-31.119],[25.58,-31.119],[40.988,-20.041],[25.983,-8.661],[19.437,-8.963]],"c":true},"ix":2},"nm":"B","mn":"ADBE Vector Shape - Group","hd":false}],"nm":"B","np":6,"cix":2,"bm":0,"ix":1,"mn":"ADBE Vector Group","hd":false}]},"fFamily":"Myriad Pro"},{"ch":"U","size":180,"style":"Semibold","w":66.6,"data":{"shapes":[{"ty":"gr","it":[{"ind":0,"ty":"sh","ix":1,"ks":{"a":0,"k":{"i":[[0,0],[0,0],[-15.71,0],[0,20.947],[0,0],[0,0],[0,0],[8.963,0],[0,13.293],[0,0]],"o":[[0,0],[0,21.35],[16.315,0],[0,0],[0,0],[0,0],[0,13.293],[-8.359,0],[0,0],[0,0]],"v":[[7.05,-67.877],[7.05,-29.004],[32.932,1.108],[60.022,-29.105],[60.022,-67.877],[47.635,-67.877],[47.635,-28.299],[33.334,-8.862],[19.437,-28.299],[19.437,-67.877]],"c":true},"ix":2},"nm":"U","mn":"ADBE Vector Shape - Group","hd":false}],"nm":"U","np":3,"cix":2,"bm":0,"ix":1,"mn":"ADBE Vector Group","hd":false}]},"fFamily":"Myriad Pro"},{"ch":"T","size":180,"style":"Semibold","w":55.4,"data":{"shapes":[{"ty":"gr","it":[{"ind":0,"ty":"sh","ix":1,"ks":{"a":0,"k":{"i":[[0,0],[0,0],[0,0],[0,0],[0,0],[0,0],[0,0],[0,0]],"o":[[0,0],[0,0],[0,0],[0,0],[0,0],[0,0],[0,0],[0,0]],"v":[[20.142,0],[32.529,0],[32.529,-57.504],[52.066,-57.504],[52.066,-67.877],[0.806,-67.877],[0.806,-57.504],[20.142,-57.504]],"c":true},"ix":2},"nm":"T","mn":"ADBE Vector Shape - Group","hd":false}],"nm":"T","np":3,"cix":2,"bm":0,"ix":1,"mn":"ADBE Vector Group","hd":false}]},"fFamily":"Myriad Pro"},{"ch":"O","size":180,"style":"Semibold","w":70.4,"data":{"shapes":[{"ty":"gr","it":[{"ind":0,"ty":"sh","ix":1,"ks":{"a":0,"k":{"i":[[19.839,0],[0,-20.847],[-19.135,0],[0,22.76]],"o":[[-19.135,0],[0,19.94],[18.732,0],[0,-19.336]],"v":[[35.852,-68.985],[3.625,-33.435],[34.845,1.108],[67.374,-34.644]],"c":true},"ix":2},"nm":"O","mn":"ADBE Vector Shape - Group","hd":false},{"ind":1,"ty":"sh","ix":2,"ks":{"a":0,"k":{"i":[[-12.286,0],[0,-12.79],[11.984,0],[0,13.797]],"o":[[12.387,0],[0,14.2],[-11.884,0],[0,-13.998]],"v":[[35.55,-59.015],[54.282,-34.14],[35.55,-8.862],[16.718,-33.636]],"c":true},"ix":2},"nm":"O","mn":"ADBE Vector Shape - Group","hd":false}],"nm":"O","np":5,"cix":2,"bm":0,"ix":1,"mn":"ADBE Vector Group","hd":false}]},"fFamily":"Myriad Pro"},{"ch":"N","size":180,"style":"Semibold","w":67.6,"data":{"shapes":[{"ty":"gr","it":[{"ind":0,"ty":"sh","ix":1,"ks":{"a":0,"k":{"i":[[0,0],[0,0],[0.504,8.762],[0,0],[-4.33,-7.452],[0,0],[0,0],[0,0],[0,0],[0,0],[-0.806,-9.064],[0,0],[4.532,7.553],[0,0],[0,0],[0,0]],"o":[[0,0],[0,-11.179],[0,0],[3.323,7.654],[0,0],[0,0],[0,0],[0,0],[0,0],[0,10.373],[0,0],[-3.122,-7.352],[0,0],[0,0],[0,0],[0,0]],"v":[[18.53,0],[18.53,-24.271],[17.926,-53.174],[18.228,-53.275],[30.414,-29.81],[48.138,0],[60.928,0],[60.928,-67.877],[49.448,-67.877],[49.448,-44.211],[50.555,-16.013],[50.354,-16.013],[38.773,-38.773],[21.249,-67.877],[7.15,-67.877],[7.15,0]],"c":true},"ix":2},"nm":"N","mn":"ADBE Vector Shape - Group","hd":false}],"nm":"N","np":3,"cix":2,"bm":0,"ix":1,"mn":"ADBE Vector Group","hd":false}]},"fFamily":"Myriad Pro"}]}